[
  {
    "endpoint": "/api/services",
    "status": 404,
    "timeMs": 1,
    "headers": {
      "content-type": "application/json; charset=utf-8",
      "x-content-type-options": "nosniff",
      "x-frame-options": "SAMEORIGIN",
      "cache-control": null,
      "x-rate-limit-remaining": null,
      "x-correlation-id": "b46861a3-9ba9-410b-8836-4d85dd084669"
    },
    "body": {
      "success": false,
      "error": {
        "code": "RESOURCE_NOT_FOUND",
        "message": "The requested resource was not found"
      }
    }
  }
]
